{
  "NetworkTables": {
    "transitory": {
      "SmartDashboard": {
        "Drivetrain": {
          "field": {
            "open": false
          },
          "modules": {
            "module-1": {
              "open": false
            },
            "open": false
          }
        }
      }
    },
    "types": {
      "/FMSInfo": "FMSInfo",
      "/Shuffleboard/Drive/Auto Route": "String Chooser",
      "/Shuffleboard/Drive/SWITCH ALLIANCE": "Command",
      "/Shuffleboard/Drive/SYNC ALLIANCE": "Command",
      "/SmartDashboard///Robot/Drivetrain/field": "Field2d",
      "/SmartDashboard//Drivetrain/field": "Field2d",
      "/SmartDashboard/InstantCommand": "Command"
    },
    "windows": {
      "/SmartDashboard///Robot/Drivetrain/field": {
        "height": 8.229599952697754,
        "image": "C:\\Users\\barta\\Documents\\Github\\Shambots5907_23CompBot\\Glass Configuration\\field23.png",
        "width": 16.459199905395508,
        "window": {
          "visible": true
        }
      },
      "/SmartDashboard//Drivetrain/field": {
        "Module-1": {
          "image": "",
          "length": 0.0,
          "width": 0.0
        },
        "Module-2": {
          "image": "",
          "length": 0.0,
          "width": 0.0
        },
        "Module-3": {
          "image": "",
          "length": 0.0,
          "width": 0.0
        },
        "Module-4": {
          "image": "",
          "length": 0.0,
          "width": 0.0
        },
        "ll": {
          "length": 0.0,
          "width": 0.0
        },
        "target": {
          "image": "",
          "length": 0.0,
          "width": 0.0
        }
      }
    }
  },
  "NetworkTables Settings": {
    "mode": "Client (NT4)",
    "serverTeam": "5907"
  }
}
